sp_ask_list_of_concurrent_chats/__init__.py
sp_ask_list_of_concurrent_chats-0.1.2.dist-info/WHEEL
sp_ask_list_of_concurrent_chats-0.1.2.dist-info/METADATA
sp_ask_list_of_concurrent_chats-0.1.2.dist-info/RECORD
